CHANGES.rst
LICENSE.txt
MANIFEST.in
README.rst
setup.py
src/kwargs_obj/__init__.py
src/kwargs_obj/kwargs_obj.py
src/kwargs_obj.egg-info/PKG-INFO
src/kwargs_obj.egg-info/SOURCES.txt
src/kwargs_obj.egg-info/dependency_links.txt
src/kwargs_obj.egg-info/requires.txt
src/kwargs_obj.egg-info/top_level.txt
src/kwargs_obj.egg-info/zip-safe
tests/test_kwarg_obj.py