Metadata-Version: 1.1
Name: kwargs-obj
Version: 1.0.0
Summary: Class that maps .__init__(self, **kwargs) to attributes.
Home-page: https://github.com/Bystroushaak/kwargs_obj
Author: Bystroushaak
Author-email: bystrousak@kitakitsune.org
License: MIT
Platform: UNKNOWN
Classifier: Intended Audience :: Developers
Classifier: Programming Language :: Python :: 2
Classifier: Programming Language :: Python :: 2.7
Classifier: License :: OSI Approved :: MIT License
